pymedphys/.pylintrc
pymedphys/__init__.py
pymedphys/__main__.py
pymedphys/_app.py
pymedphys/_base/__init__.py
pymedphys/_base/delivery.py
pymedphys/_config.py
pymedphys/_data/__init__.py
pymedphys/_data/download.py
pymedphys/_data/hashes.json
pymedphys/_data/retry.py
pymedphys/_data/upload.py
pymedphys/_data/urls.json
pymedphys/_data/zenodo.json
pymedphys/_data/zenodo.py
pymedphys/_delivery.py
pymedphys/_dev/__init__.py
pymedphys/_dev/build.py
pymedphys/_dev/docs.py
pymedphys/_dev/paths.py
pymedphys/_dev/propagate.py
pymedphys/_dev/tests.py
pymedphys/_dicom/__init__.py
pymedphys/_dicom/anonymise/__init__.py
pymedphys/_dicom/anonymise/api.py
pymedphys/_dicom/anonymise/core.py
pymedphys/_dicom/anonymise/identifying_keywords.json
pymedphys/_dicom/anonymise/strategy.py
pymedphys/_dicom/collection.py
pymedphys/_dicom/connect/__init__.py
pymedphys/_dicom/connect/base.py
pymedphys/_dicom/connect/listen.py
pymedphys/_dicom/connect/send.py
pymedphys/_dicom/constants/__init__.py
pymedphys/_dicom/constants/baseline_dicom_dictionary.json
pymedphys/_dicom/constants/baseline_repeaters_dictionary.json
pymedphys/_dicom/constants/core.py
pymedphys/_dicom/coords.py
pymedphys/_dicom/create.py
pymedphys/_dicom/ct/__init__.py
pymedphys/_dicom/ct/extend.py
pymedphys/_dicom/delivery/__init__.py
pymedphys/_dicom/delivery/core.py
pymedphys/_dicom/delivery/utilities.py
pymedphys/_dicom/dose.py
pymedphys/_dicom/header.py
pymedphys/_dicom/orientation.py
pymedphys/_dicom/rtplan/__init__.py
pymedphys/_dicom/rtplan/adjust.py
pymedphys/_dicom/rtplan/build.py
pymedphys/_dicom/rtplan/core.py
pymedphys/_dicom/sorting.py
pymedphys/_dicom/structure/__init__.py
pymedphys/_dicom/structure/merge.py
pymedphys/_dicom/uid.py
pymedphys/_dicom/utilities/__init__.py
pymedphys/_dicom/utilities/display.py
pymedphys/_dicom/utilities/files.py
pymedphys/_electronfactors/__init__.py
pymedphys/_electronfactors/core.py
pymedphys/_electronfactors/visualisation.py
pymedphys/_experimental/__init__.py
pymedphys-0.40.0.dist-info/entry_points.txt
pymedphys-0.40.0.dist-info/LICENSE
pymedphys-0.40.0.dist-info/METADATA
pymedphys-0.40.0.dist-info/WHEEL
pymedphys-0.40.0.dist-info/RECORD
