Metadata-Version: 2.1
Name: pymedphys
Version: 0.40.0
Summary: Medical Physics library
Home-page: https://pymedphys.com
License: Apache-2.0
Author: PyMedPhys Contributors
Author-email: developers@pymedphys.com
Requires-Python: >=3.8, !=2.7.*, !=3.0.*, !=3.1.*, !=3.2.*, !=3.3.*, !=3.4.*, !=3.5.*, !=3.6.*, !=3.7.*, !=3.12.*
Classifier: Development Status :: 4 - Beta
Classifier: Intended Audience :: Healthcare Industry
Classifier: Intended Audience :: Science/Research
Classifier: License :: OSI Approved :: Apache Software License
Classifier: Programming Language :: Python :: 3
Classifier: Programming Language :: Python :: 3.8
Classifier: Programming Language :: Python :: 3.9
Classifier: Programming Language :: Python :: 3.10
Classifier: Programming Language :: Python :: 3.11
Classifier: Topic :: Scientific/Engineering :: Medical Science Apps.
Classifier: Topic :: Scientific/Engineering :: Physics
Provides-Extra: all
Provides-Extra: cli
Provides-Extra: comparables
Provides-Extra: dev
Provides-Extra: dicom
Provides-Extra: docs
Provides-Extra: doctests
Provides-Extra: icom
Provides-Extra: mosaiq
Provides-Extra: propagate
Provides-Extra: speedups
Provides-Extra: tests
Provides-Extra: user
Requires-Dist: Pillow (>=9.0.0) ; extra == "all" or extra == "user"
Requires-Dist: PyYAML ; extra == "all" or extra == "user"
Requires-Dist: astroid ; extra == "all" or extra == "tests"
Requires-Dist: attrs ; extra == "all" or extra == "mosaiq" or extra == "user"
Requires-Dist: black (>=22.3.0) ; extra == "all" or extra == "dev" or extra == "doctests" or extra == "propagate"
Requires-Dist: dbfread ; extra == "all" or extra == "user"
Requires-Dist: dicompyler-core ; extra == "all" or extra == "user"
Requires-Dist: doc8 ; extra == "all" or extra == "dev"
Requires-Dist: flashgamma ; extra == "comparables"
Requires-Dist: imageio ; extra == "all" or extra == "user"
Requires-Dist: interpolation (>=2.1.0) ; extra == "speedups"
Requires-Dist: ipython (>=7.31.1) ; extra == "all" or extra == "docs"
Requires-Dist: jupyter-book (>=0.12.0) ; extra == "all" or extra == "docs"
Requires-Dist: keyring ; extra == "all" or extra == "user"
Requires-Dist: matplotlib ; extra == "all" or extra == "docs" or extra == "user"
Requires-Dist: mypy ; extra == "all" or extra == "dev"
Requires-Dist: natsort ; extra == "all" or extra == "user"
Requires-Dist: networkx ; extra == "all" or extra == "docs"
Requires-Dist: numpy (>=1.20.2) ; extra == "all" or extra == "docs" or extra == "icom" or extra == "user"
Requires-Dist: packaging ; extra == "all" or extra == "user"
Requires-Dist: pandas (>=1.0.0) ; extra == "all" or extra == "mosaiq" or extra == "user"
Requires-Dist: pre-commit ; extra == "all" or extra == "dev"
Requires-Dist: psutil ; extra == "all" or extra == "tests"
Requires-Dist: pydicom (>=2.0.0) ; extra == "all" or extra == "dicom" or extra == "docs" or extra == "user"
Requires-Dist: pylibjpeg-libjpeg (>=1.3.2) ; extra == "all" or extra == "user"
Requires-Dist: pylint ; extra == "all" or extra == "tests"
Requires-Dist: pymssql ; extra == "all" or extra == "mosaiq" or extra == "user"
Requires-Dist: pynetdicom ; extra == "all" or extra == "dicom" or extra == "user"
Requires-Dist: pytest ; extra == "all" or extra == "tests"
Requires-Dist: pytest-rerunfailures ; extra == "all" or extra == "tests"
Requires-Dist: pytest-sugar ; extra == "all" or extra == "tests"
Requires-Dist: python-dateutil ; extra == "all" or extra == "tests" or extra == "user"
Requires-Dist: pywin32 (>=301) ; (sys_platform == "win32") and (extra == "all" or extra == "user")
Requires-Dist: readme-renderer ; extra == "all" or extra == "dev"
Requires-Dist: requests ; extra == "all" or extra == "user"
Requires-Dist: rope ; extra == "all" or extra == "dev"
Requires-Dist: scikit-learn ; extra == "all" or extra == "mosaiq" or extra == "user"
Requires-Dist: scipy ; extra == "all" or extra == "docs" or extra == "user"
Requires-Dist: setuptools
Requires-Dist: shapely (>=1.7.0) ; extra == "all" or extra == "user"
Requires-Dist: sphinx-argparse ; extra == "all" or extra == "docs"
Requires-Dist: sphinx-book-theme ; extra == "all" or extra == "docs" or extra == "doctests"
Requires-Dist: sqlalchemy ; extra == "all" or extra == "mosaiq" or extra == "user"
Requires-Dist: streamlit (>=1.29.0,<1.30.0) ; extra == "all" or extra == "user"
Requires-Dist: streamlit-ace ; extra == "all" or extra == "user"
Requires-Dist: tabulate ; extra == "all" or extra == "dev" or extra == "doctests"
Requires-Dist: timeago ; extra == "all" or extra == "user"
Requires-Dist: toml ; extra == "all" or extra == "cli" or extra == "docs" or extra == "mosaiq" or extra == "user"
Requires-Dist: tomlkit
Requires-Dist: tqdm ; extra == "all" or extra == "docs" or extra == "tests" or extra == "user"
Requires-Dist: typing-extensions
Requires-Dist: watchdog ; extra == "all" or extra == "user"
Requires-Dist: xmltodict ; extra == "all" or extra == "user"
Project-URL: Documentation, https://docs.pymedphys.com
Project-URL: Repository, https://github.com/pymedphys/pymedphys
